spookyai/__init__.py
spookyai-0.1.28.dist-info/METADATA
spookyai-0.1.28.dist-info/WHEEL
spookyai-0.1.28.dist-info/entry_points.txt
spookyai-0.1.28.dist-info/licenses/LICENSE
spookyai-0.1.28.dist-info/RECORD
